bare_estate/__init__.py
bare_estate/__main__.py
bare_estate/cli.py
bare_estate/commands.py
bare_estate/config.py
bare_estate-0.6.dist-info/METADATA
bare_estate-0.6.dist-info/WHEEL
bare_estate-0.6.dist-info/entry_points.txt
bare_estate-0.6.dist-info/licenses/LICENSE
bare_estate-0.6.dist-info/RECORD
