Metadata-Version: 2.3
Name: bare_estate
Version: 0.6
Summary: Manage your dotfiles seamlessly
Project-URL: Homepage, https://github.com/llucasls/bare-estate
Author-email: "Lucas L. S. Haine" <lucaslshaine@gmail.com>
License-File: LICENSE
Classifier: License :: OSI Approved :: MIT License
Classifier: Operating System :: POSIX
Classifier: Programming Language :: Python :: 3
Requires-Python: >=3.7
Requires-Dist: toml
